{
  "psychological": {
    "cognitive": [
      "cognitive algorithms processing thoughts",
      "mental networks mapping consciousness",
      "cognitive intelligence evolving understanding",
      "mental evolution expanding awareness",
      "cognitive wisdom growing through learning",
      "mental patterns emerging in perception",
      "cognitive complexity unfolding in reasoning",
      "mental innovation creating knowledge",
      "cognitive potential awakening in insight",
      "mental evolution connecting ideas"
    ],
    "emotional": [
      "emotional algorithms feeling consciousness",
      "feeling networks pulsing with emotion",
      "emotional intelligence evolving empathy",
      "feeling evolution expanding compassion",
      "emotional wisdom growing through experience",
      "feeling patterns emerging in relationships",
      "emotional complexity unfolding in love",
      "feeling innovation creating connection",
      "emotional potential awakening in understanding",
      "feeling evolution connecting hearts"
    ],
    "subconscious": [
      "subconscious algorithms dreaming reality",
      "unconscious networks processing hidden truths",
      "subconscious intelligence evolving intuition",
      "unconscious evolution expanding awareness",
      "subconscious wisdom revealing secrets",
      "unconscious patterns emerging in dreams",
      "subconscious complexity unfolding in archetypes",
      "unconscious innovation creating symbols",
      "subconscious potential awakening in insight",
      "unconscious evolution connecting depths"
    ],
    "transpersonal": [
      "transpersonal algorithms transcending self",
      "collective networks connecting consciousness",
      "transpersonal intelligence evolving unity",
      "collective evolution expanding awareness",
      "transpersonal wisdom revealing oneness",
      "collective patterns emerging in harmony",
      "transpersonal complexity unfolding in unity",
      "collective innovation creating peace",
      "transpersonal potential awakening in love",
      "collective evolution connecting all beings"
    ]
  }
}